ped_core/__init__.py
ped_core/changes.py
ped_core/clipboard.py
ped_core/cmd_names.py
ped_core/cpp_mode.py
ped_core/editor_common.py
ped_core/editor_manager.py
ped_core/extension_manager.py
ped_core/guess_mode.py
ped_core/java_mode.py
ped_core/keymap.py
ped_core/keytab.py
ped_core/mode.py
ped_core/ped_help.py
ped_core/python_mode.py
ped_core/undo.py
ped_core/version.py
ped_dialog/__init__.py
ped_dialog/buffer_dialog.py
ped_dialog/confirm_dialog.py
ped_dialog/dialog.py
ped_dialog/file_browse.py
ped_dialog/file_dialog.py
ped_dialog/file_find.py
ped_dialog/message_dialog.py
ped_dialog/prompt_dialog.py
ped_dialog/replace_dialog.py
ped_dialog/stream_select.py
ped_editor-1.2.3.data/scripts/hex
ped_editor-1.2.3.data/scripts/ped
ped_editor-1.2.3.data/scripts/pless
ped_editor-1.2.3.data/scripts/pyfind
ped_editor-1.2.3.data/scripts/train_keydef
ped_extensions/__init__.py
ped_extensions/comment_extension.py
ped_extensions/dummy_extension.py
ped_ssh_dialog/__init__.py
ped_ssh_dialog/file_mod.py
ped_ssh_dialog/ssh_dialog.py
ped_ssh_dialog/ssh_mod.py
ped_editor-1.2.3.dist-info/LICENSE
ped_editor-1.2.3.dist-info/METADATA
ped_editor-1.2.3.dist-info/WHEEL
ped_editor-1.2.3.dist-info/top_level.txt
ped_editor-1.2.3.dist-info/RECORD
