Metadata-Version: 2.1
Name: ped-editor
Version: 1.2.3
Summary: A code editor written in python
Home-page: http://github.com/jpfxgood/ped
Author: James Goodwin
Author-email: ped-editor@jlgoodwin.com
License: MIT
Keywords: editor,ide
Platform: UNKNOWN
Classifier: Programming Language :: Python :: 3
Classifier: License :: OSI Approved :: MIT License
Classifier: Operating System :: OS Independent
Requires-Python: >=3.6
Requires-Dist: Pygments (>=2.1)
Requires-Dist: paramiko (>=2.0.9)
